sentient/__init__.py
sentient/__main__.py
sentient/config/__init__.py
sentient/config/config.py
sentient/core/agent/__init__.py
sentient/core/agent/agent.py
sentient/core/agent/base.py
sentient/core/memory/__init__.py
sentient/core/memory/ltm.py
sentient/core/models/__init__.py
sentient/core/models/models.py
sentient/core/orchestrator/orchestrator.py
sentient/core/prompts/__init__.py
sentient/core/prompts/prompts.py
sentient/core/skills/__init__.py
sentient/core/skills/click_using_selector.py
sentient/core/skills/enter_text_and_click.py
sentient/core/skills/enter_text_using_selector.py
sentient/core/skills/get_dom_with_content_type.py
sentient/core/skills/get_screenshot.py
sentient/core/skills/get_url.py
sentient/core/skills/get_user_input.py
sentient/core/skills/open_url.py
sentient/core/skills/pdf_text_extractor.py
sentient/core/skills/press_key_combination.py
sentient/core/skills/upload_file.py
sentient/core/web_driver/__init__.py
sentient/core/web_driver/playwright.py
sentient/task_instructions/task_instructions.txt
sentient/utils/__init__.py
sentient/utils/_pydantic.py
sentient/utils/cli_helper.py
sentient/utils/dom_helper.py
sentient/utils/dom_mutation_observer.py
sentient/utils/extract_json.py
sentient/utils/function_utils.py
sentient/utils/get_detailed_accessibility_tree.py
sentient/utils/logger.py
sentient/utils/message_type.py
sentient/utils/providers.py
sentient/utils/ui_messagetype.py
sentient-0.1.10.dist-info/LICENSE
sentient-0.1.10.dist-info/METADATA
sentient-0.1.10.dist-info/WHEEL
sentient-0.1.10.dist-info/RECORD
