Metadata-Version: 2.1
Name: sentient
Version: 0.1.10
Summary: 
Author: nischalj10
Author-email: nischalj10@gmail.com
Requires-Python: >=3.9,<4.0
Classifier: Programming Language :: Python :: 3
Classifier: Programming Language :: Python :: 3.9
Classifier: Programming Language :: Python :: 3.10
Classifier: Programming Language :: Python :: 3.11
Classifier: Programming Language :: Python :: 3.12
Requires-Dist: aiohttp (>=3.10.2,<4.0.0)
Requires-Dist: anthropic (>=0.34.2,<0.35.0)
Requires-Dist: boto3 (>=1.34.157,<2.0.0)
Requires-Dist: colorama (>=0.4.6,<0.5.0)
Requires-Dist: eval-type-backport (>=0.2.0,<0.3.0)
Requires-Dist: google-generativeai (>=0.8.1,<0.9.0)
Requires-Dist: groq (>=0.11.0,<0.12.0)
Requires-Dist: instructor (==1.4.2)
Requires-Dist: jsonref (>=1.1.0,<2.0.0)
Requires-Dist: langsmith (>=0.1.104,<0.2.0)
Requires-Dist: litellm (>=1.48.8,<2.0.0)
Requires-Dist: openai (>=1.40.1,<2.0.0)
Requires-Dist: pdfplumber (==0.11.2)
Requires-Dist: pydantic (>=2.8.2,<3.0.0)
Requires-Dist: pytest-playwright (>=0.5.1,<0.6.0)
Requires-Dist: python-dotenv (>=1.0.1,<2.0.0)
Requires-Dist: python-json-logger (>=2.0.7,<3.0.0)
Requires-Dist: ruff (>=0.5.6,<0.6.0)
Requires-Dist: setuptools (>=72.1.0,<73.0.0)
Requires-Dist: tabulate (>=0.9.0,<0.10.0)
Requires-Dist: termcolor (>=2.4.0,<3.0.0)
Requires-Dist: tiktoken (>=0.7.0,<0.8.0)
Requires-Dist: typing-extensions (>=4.12.2,<5.0.0)
